MANIFEST.in
README.rst
requirements.txt
setup.py
django_musette.egg-info/PKG-INFO
django_musette.egg-info/SOURCES.txt
django_musette.egg-info/dependency_links.txt
django_musette.egg-info/not-zip-safe
django_musette.egg-info/requires.txt
django_musette.egg-info/top_level.txt
musette/__init__.py
musette/admin.py
musette/apps.py
musette/consumers.py
musette/context_processors.py
musette/decorators.py
musette/email.py
musette/feeds.py
musette/forms.py
musette/middleware.py
musette/mixins.py
musette/models.py
musette/realtime.py
musette/routing.py
musette/settings.py
musette/signals.py
musette/tests.py
musette/urls.py
musette/utils.py
musette/validators.py
musette/version.py
musette/views.py
musette/widgets.py
musette/api/__init__.py
musette/api/permissions.py
musette/api/serializers.py
musette/api/urls.py
musette/api/views.py
musette/locale/en/LC_MESSAGES/django.mo
musette/locale/en/LC_MESSAGES/django.po
musette/locale/es/LC_MESSAGES/django.mo
musette/locale/es/LC_MESSAGES/django.po
musette/locale/it/LC_MESSAGES/django.mo
musette/locale/it/LC_MESSAGES/django.po
musette/management/__init__.py
musette/management/commands/__init__.py
musette/management/commands/create_profile_superadmin.py
musette/migrations/0001_initial.py
musette/migrations/0002_profile_receiveemails.py
musette/migrations/0003_auto_20170714_2246.py
musette/migrations/0004_auto_20170714_2248.py
musette/migrations/__init__.py
musette/static/musette/css/custom.css
musette/static/musette/css/style.min.css
musette/static/musette/css/styles.css
musette/static/musette/img/ajax.gif
musette/static/musette/img/favicon.png
musette/static/musette/img/feed.png
musette/static/musette/img/logo.png
musette/static/musette/img/profile.png
musette/static/musette/js/textareas.js
musette/static/musette/js/libs/jquery/jquery-2.1.3.min.js
musette/static/musette/js/libs/toastr/.gitattributes
musette/static/musette/js/libs/toastr/.jscsrc
musette/static/musette/js/libs/toastr/.jshintrc
musette/static/musette/js/libs/toastr/.npmignore
musette/static/musette/js/libs/toastr/.travis.yml
musette/static/musette/js/libs/toastr/build/toastr.css
musette/static/musette/js/libs/toastr/build/toastr.js.map
